dpulse/.github/ISSUE_TEMPLATE/bug_report.md
dpulse/.github/ISSUE_TEMPLATE/custom.md
dpulse/.github/ISSUE_TEMPLATE/feature_request.md
dpulse/.github/workflows/codeql.yml
dpulse/.github/workflows/python-package.yml
dpulse/.readthedocs.yaml
dpulse/__init__.py
dpulse/apis/__init__.py
dpulse/apis/api_keys.db
dpulse/apis/api_keys_reference.db
dpulse/apis/api_securitytrails.py
dpulse/apis/api_virustotal.py
dpulse/CODE_OF_CONDUCT.md
dpulse/datagather_modules/__init__.py
dpulse/datagather_modules/crawl_processor.py
dpulse/datagather_modules/data_assembler.py
dpulse/datagather_modules/networking_processor.py
dpulse/docs/__init__.py
dpulse/docs/dpulse-docs/docs/api.md
dpulse/docs/dpulse-docs/docs/basic_scan.md
dpulse/docs/dpulse-docs/docs/contact_dev.md
dpulse/docs/dpulse-docs/docs/demo.md
dpulse/docs/dpulse-docs/docs/dorking.md
dpulse/docs/dpulse-docs/docs/getting_started.md
dpulse/docs/dpulse-docs/docs/index.md
dpulse/docs/dpulse-docs/docs/pagesearch.md
dpulse/docs/dpulse-docs/docs/pagesearch_sitemap.md
dpulse/docs/dpulse-docs/docs/reporting.md
dpulse/docs/dpulse-docs/mkdocs.yml
dpulse/dorking/__init__.py
dpulse/dorking/adminpanels_dorking.db
dpulse/dorking/basic_dorking.db
dpulse/dorking/db_creator.py
dpulse/dorking/dorking_handler.py
dpulse/dorking/files_dorking.db
dpulse/dorking/iot_dorking.db
dpulse/dorking/proxies_rotator.py
dpulse/dorking/ua_rotator.py
dpulse/dorking/webstructure_dorking.db
dpulse/dpulse.py
dpulse/installer.bat
dpulse/installer.sh
dpulse/pagesearch/__init__.py
dpulse/pagesearch/pagesearch_deepsearch.py
dpulse/pagesearch/pagesearch_main.py
dpulse/pagesearch/pagesearch_parsers.py
dpulse/report_examples/html_report_example/01-robots.txt
"dpulse/report_examples/html_report_example/hackthissiteorg_(28-12-2024, 09h17m49s).html"
dpulse/report_examples/html_report_example/ps_documents/extracted_About%20the%20HackThisSite%20Mirror.txt
dpulse/report_examples/xlsx_report_example/01-robots.txt
dpulse-1.2.dist-info/entry_points.txt
dpulse-1.2.dist-info/LICENSE
dpulse-1.2.dist-info/METADATA
dpulse-1.2.dist-info/WHEEL
dpulse-1.2.dist-info/RECORD
