Metadata-Version: 2.1
Name: dpulse
Version: 1.2
Summary: Convenient,fast and user-friendly collector of domain information from Open-Sources
Home-page: https://pypi.org/manage/projects/dpulse
License: MIT
Author: OSINT-TECHNOLOGIES
Author-email: osint.technologies@gmail.com
Requires-Python: >=3.10,<4.0
Classifier: Development Status :: 5 - Production/Stable
Classifier: Intended Audience :: Information Technology
Classifier: License :: OSI Approved :: MIT License
Classifier: Natural Language :: English
Classifier: Operating System :: OS Independent
Classifier: Programming Language :: Python :: 3
Classifier: Programming Language :: Python :: 3.10
Classifier: Programming Language :: Python :: 3.11
Classifier: Programming Language :: Python :: 3.12
Requires-Dist: Jinja2 (>=3.1.5,<4.0.0)
Requires-Dist: MarkupSafe (==2.1.5)
Requires-Dist: MechanicalSoup (==1.3.0)
Requires-Dist: PyMuPDF (==1.24.7)
Requires-Dist: beautifulsoup4 (==4.12.2)
Requires-Dist: builtwith (==1.3.4)
Requires-Dist: certifi (>=2024.07.04)
Requires-Dist: charset-normalizer (==3.3.2)
Requires-Dist: colorama (==0.4.6)
Requires-Dist: dnspython (==2.6.1)
Requires-Dist: idna (==3.7)
Requires-Dist: lxml (==5.2.2)
Requires-Dist: openpyxl (==3.1.2)
Requires-Dist: pyfiglet (==1.0.2)
Requires-Dist: python-whois (==0.9.4)
Requires-Dist: requests (==2.32.3)
Requires-Dist: rich (==13.7.1)
Requires-Dist: soupsieve (==2.5)
Requires-Dist: urllib3 (==2.2.2)
Project-URL: Repository, https://github.com/OSINT-TECHNOLOGIES/dpulse
